bold_smart_lock/__init__.py
bold_smart_lock/auth.py
bold_smart_lock/bold_smart_lock.py
bold_smart_lock/const.py
bold_smart_lock/enums.py
bold_smart_lock/exceptions.py
bold_smart_lock-0.3.9.dist-info/LICENSE
bold_smart_lock-0.3.9.dist-info/METADATA
bold_smart_lock-0.3.9.dist-info/WHEEL
bold_smart_lock-0.3.9.dist-info/top_level.txt
bold_smart_lock-0.3.9.dist-info/RECORD
