Metadata-Version: 2.1
Name: bold-smart-lock
Version: 0.3.9
Summary: Python library to communicate with Bold Smart Lock (https://boldsmartlock.com)
Home-page: https://github.com/westenberg/bold_smart_lock
Author: Westenberg
Author-email: lauren@westenberg.dev
License: MIT
Keywords: bold,smart lock,home automation
Classifier: Environment :: Other Environment
Classifier: Intended Audience :: Developers
Classifier: License :: OSI Approved :: GNU Lesser General Public License v3 or later (LGPLv3+)
Classifier: Operating System :: OS Independent
Classifier: Programming Language :: Python
Classifier: Programming Language :: Python :: 3.9
Classifier: Topic :: Home Automation
Classifier: Topic :: Software Development :: Libraries :: Python Modules
License-File: LICENSE
Requires-Dist: aiohttp
Requires-Dist: asyncio
